setup.py
KralEngine.egg-info/PKG-INFO
KralEngine.egg-info/SOURCES.txt
KralEngine.egg-info/dependency_links.txt
KralEngine.egg-info/requires.txt
KralEngine.egg-info/top_level.txt
kralengine/__init__.py
kralengine/actor.py
kralengine/animation.py
kralengine/collider.py
kralengine/input.py
kralengine/light.py
kralengine/line.py
kralengine/main.py
kralengine/shapes.py
kralengine/size.py
kralengine/text.py
kralengine/types.py
kralengine/utils.py