Metadata-Version: 1.0
Name: KralEngine
Version: 1.2
Summary: A game engine based pygame for python
Home-page: UNKNOWN
Author: thekralgame
Author-email: mandiracieyuphan@gmail.com
License: MIT
Platform: UNKNOWN
